<?xml version="1.0" encoding="utf-8"?>
	<annotation>
		<folder>images</folder>
		<filename>000000000064.jpg</filename>
		<size>
			<width>480</width>
			<height>640</height>
			<depth>3</depth>
		</size>
		<object>
			<name>car</name>
			<pose>Unspecified</pose>
			<truncated>0</truncated>
			<difficult>0</difficult>
			<bndbox>
				<xmin>52.36007999999998</xmin>
				<ymin>387.76991999999996</ymin>
				<xmax>228.72024</xmax>
				<ymax>545.38976</ymax>
			</bndbox>
		</object>
		<object>
			<name>truck</name>
			<pose>Unspecified</pose>
			<truncated>0</truncated>
			<difficult>0</difficult>
			<bndbox>
				<xmin>52.640160000000016</xmin>
				<ymin>353.77987200000007</ymin>
				<xmax>177.22032000000002</xmax>
				<ymax>413.24988800000006</ymax>
			</bndbox>
		</object>
		<object>
			<name>stop sign</name>
			<pose>Unspecified</pose>
			<truncated>0</truncated>
			<difficult>0</difficult>
			<bndbox>
				<xmin>115.84008</xmin>
				<ymin>226.58975999999998</ymin>
				<xmax>152.86007999999998</xmax>
				<ymax>301.75968</ymax>
			</bndbox>
		</object>
		<object>
			<name>clock</name>
			<pose>Unspecified</pose>
			<truncated>0</truncated>
			<difficult>0</difficult>
			<bndbox>
				<xmin>112.04015999999999</xmin>
				<ymin>42.190079999999995</ymin>
				<xmax>266.34000000000003</xmax>
				<ymax>194.49984</ymax>
			</bndbox>
		</object>
	</annotation>
