<?xml version="1.0" encoding="utf-8"?>
	<annotation>
		<folder>images</folder>
		<filename>000000000072.jpg</filename>
		<size>
			<width>427</width>
			<height>640</height>
			<depth>3</depth>
		</size>
		<object>
			<name>giraffe</name>
			<pose>Unspecified</pose>
			<truncated>0</truncated>
			<difficult>0</difficult>
			<bndbox>
				<xmin>136.63017899999997</xmin>
				<ymin>129.44000000000003</ymin>
				<xmax>425.71003299999995</xmax>
				<ymax>628.49024</ymax>
			</bndbox>
		</object>
		<object>
			<name>giraffe</name>
			<pose>Unspecified</pose>
			<truncated>0</truncated>
			<difficult>0</difficult>
			<bndbox>
				<xmin>50.450050000000005</xmin>
				<ymin>72.07008000000002</ymin>
				<xmax>283.96012399999995</xmax>
				<ymax>640.0003200000001</ymax>
			</bndbox>
		</object>
	</annotation>
